[{"Guid":"e7aacc4a-ccfd-43e7-85f5-b2e241172945","Name":"","Family":"","NationalCode":"","Address":"","PhoneNumber":"77"},{"Guid":"1cfe6bda-f7fc-4fea-b399-734956ab6cf1","Name":"","Family":"","NationalCode":"","Address":"","PhoneNumber":"77"},{"Guid":"73fbea57-7ab9-48cc-bdff-1981d103ecad","Name":"","Family":"","NationalCode":"","Address":"","PhoneNumber":"77"},{"Guid":"6d840077-574c-433f-afd8-768e550aedc5","Name":"","Family":"","NationalCode":"","Address":"","PhoneNumber":"88"},{"Guid":"5f36ca98-19fa-4978-981e-35983da5ca1a","Name":"","Family":"","NationalCode":"","Address":"","PhoneNumber":"09"},{"Guid":"8061cc05-d9e3-47f9-8e6d-f6c85276ca57","Name":"رضا","Family":"عباسی","NationalCode":"34232432","Address":"شیراز","PhoneNumber":"093743213"},{"Guid":"cdc02a92-cd2b-47e3-9d61-1e6c7c7a7582","Name":"رضا","Family":"رضایی","NationalCode":"01234567890","Address":"تهران","PhoneNumber":"09121000000"},{"Guid":"af37dd61-a7af-4635-8759-0389beb18844","Name":"محمد","Family":"محمدی","NationalCode":"9876543217","Address":"تهران","PhoneNumber":"09122000000"}]